{
  "title": "YOLOv5s Face 640x480 ONNX MQ",
  "description": "A YOLOv5s model specialized for face detection, optimized for 640x480 resolution using ONNX with mixed quantization.",
  "ai_framework": "synap",
  "domain": "vision",
  "sub_domain": "objectDetection",
  "related_domain": "face",
  "processors": [
    "SL1680"
  ],
  "dev_kit": "Astra Machina Dev Kit",
  "model_size": "",
  "path": "docs/models/sl/sl1600/object_detection/face/model/yolov5s_face_640x480_onnx/yolov5s_face_640x480_onnx_mq",
  "image_dimensions": {
    "input": "640x480",
    "output": "various resolutions based on model configuration"
  },
  "website": "https://developer.synaptics.com/models/sl/sl1600/object_detection/face/model/yolov5s_face_640x480_onnx/yolov5s_face_640x480_onnx_mq",
  "json_github": "https://github.com/syna-astra-dev/synap-models/blob/main/object_detection/face/model/yolov5s_face_640x480_onnx/yolov5s_face_640x480_onnx_mq_test.json",
  "yaml_github": "https://github.com/syna-astra-dev/synap-models/blob/main/object_detection/face/model/yolov5s_face_640x480_onnx/yolov5s_face_640x480_onnx_mq.yaml",
  "public": "true",
  "hf_download": "",
  "ms_download": "",
  "hf_link": "",
  "ms_link": "",
  "model_image": "",
  "model_gif": "",
  "yaml_content": {
    "data_layout": "default",
    "inputs": [
      {
        "means": [
          0,
          0,
          0
        ],
        "scale": 255
      }
    ],
    "outputs": [
      {
        "dequantize": true,
        "name": "349",
        "format": "yolov5 landmarks=5 transposed=1 anchors=[[],[],[],[4,5,8,10,13,16],[23,29,43,55,73,105],[146,217,231,300,335,433]]"
      },
      {
        "dequantize": true,
        "name": "369",
        "format": "yolov5"
      },
      {
        "dequantize": true,
        "name": "389",
        "format": "yolov5"
      }
    ],
    "quantization": {
      "data_type": {
        "*": "uint8",
        "Concat_155...": "int16"
      },
      "dataset": [
        "../../widerface/WIDER_val/images/[1-2]*/*.jpg"
      ]
    }
  },
  "performance": {
    "sl1640": {
      "offline": {
        "inference-time": 59.63,
        "init-time": 27.31
      },
      "online": {}
    },
    "sl1680": {
      "offline": {
        "inference-time": 31.88,
        "init-time": 13
      },
      "online": {}
    }
  }
}